LICENSE.txt
MANIFEST.in
README.md
pyproject.toml
setup.py
dedalus/__init__.py
dedalus/__main__.py
dedalus/dedalus.cfg
dedalus/public.py
dedalus.egg-info/PKG-INFO
dedalus.egg-info/SOURCES.txt
dedalus.egg-info/dependency_links.txt
dedalus.egg-info/entry_points.txt
dedalus.egg-info/requires.txt
dedalus.egg-info/top_level.txt
dedalus/core/__init__.py
dedalus/core/arithmetic.py
dedalus/core/basis.py
dedalus/core/coords.py
dedalus/core/distributor.py
dedalus/core/domain.py
dedalus/core/evaluator.py
dedalus/core/field.py
dedalus/core/future.py
dedalus/core/operators.py
dedalus/core/problems.py
dedalus/core/solvers.py
dedalus/core/subsystems.py
dedalus/core/system.py
dedalus/core/timesteppers.py
dedalus/core/transforms.py
dedalus/core/transposes.pyx
dedalus/extras/__init__.py
dedalus/extras/flow_tools.py
dedalus/extras/plot_tools.py
dedalus/extras/quick_domains.py
dedalus/libraries/__init__.py
dedalus/libraries/matsolvers.py
dedalus/libraries/spin_recombination.pyx
dedalus/libraries/dedalus_sphere/__init__.py
dedalus/libraries/dedalus_sphere/annulus.py
dedalus/libraries/dedalus_sphere/ball_wrapper.py
dedalus/libraries/dedalus_sphere/clenshaw.py
dedalus/libraries/dedalus_sphere/jacobi.py
dedalus/libraries/dedalus_sphere/old_intertwiner.py
dedalus/libraries/dedalus_sphere/operators.py
dedalus/libraries/dedalus_sphere/shell.py
dedalus/libraries/dedalus_sphere/sphere.py
dedalus/libraries/dedalus_sphere/sphere_wrapper.py
dedalus/libraries/dedalus_sphere/spin_operators.py
dedalus/libraries/dedalus_sphere/timesteppers.py
dedalus/libraries/dedalus_sphere/tuple_tools.py
dedalus/libraries/dedalus_sphere/zernike.py
dedalus/libraries/fftw/__init__.py
dedalus/libraries/fftw/fftw_c_api.pxd
dedalus/libraries/fftw/fftw_wrappers.pyx
dedalus/tests/__init__.py
dedalus/tests/ball_diffusion_analytical_eigenvalues.py
dedalus/tests/test_cartesian_ncc.py
dedalus/tests/test_cartesian_operators.py
dedalus/tests/test_cfl.py
dedalus/tests/test_clenshaw.py
dedalus/tests/test_cylinder_calculus.py
dedalus/tests/test_cylinder_ncc.py
dedalus/tests/test_cylinder_operators.py
dedalus/tests/test_evp.py
dedalus/tests/test_fourier_operators.py
dedalus/tests/test_grid_operators.py
