Metadata-Version: 2.4
Name: dedalus
Version: 3.0.5
Summary: A flexible framework for solving PDEs with modern spectral methods.
Home-page: http://dedalus-project.org
Author: Keaton J. Burns
Author-email: keaton.burns@gmail.com
License: GPL3
Classifier: Programming Language :: Python :: 3
Requires-Python: >=3.9
License-File: LICENSE.txt
Requires-Dist: docopt
Requires-Dist: h5py>=3.0.0
Requires-Dist: matplotlib>=3.7.0
Requires-Dist: mpi4py>=2.0.0
Requires-Dist: numexpr
Requires-Dist: numpy>=1.20.0
Requires-Dist: py
Requires-Dist: pytest
Requires-Dist: pytest-benchmark
Requires-Dist: pytest-cov
Requires-Dist: pytest-xdist
Requires-Dist: scipy>=1.4.0
Requires-Dist: xarray
Dynamic: author
Dynamic: author-email
Dynamic: classifier
Dynamic: description
Dynamic: description-content-type
Dynamic: home-page
Dynamic: license
Dynamic: license-file
Dynamic: requires-dist
Dynamic: requires-python
Dynamic: summary
